[{"subarea_name":"足柄上郡大井町金子","total_posting":384,"recently_posting":26,"note":null},{"subarea_name":"足柄上郡大井町金手","total_posting":478,"recently_posting":18,"note":null},{"subarea_name":"足柄上郡大井町高尾","total_posting":66,"recently_posting":38,"note":null},{"subarea_name":"足柄上郡大井町山田","total_posting":196,"recently_posting":50,"note":null},{"subarea_name":"足柄上郡大井町篠窪","total_posting":850,"recently_posting":6,"note":null},{"subarea_name":"足柄上郡大井町上大井","total_posting":909,"recently_posting":33,"note":null},{"subarea_name":"足柄上郡大井町西大井","total_posting":485,"recently_posting":11,"note":null},{"subarea_name":"足柄上郡大井町赤田","total_posting":962,"recently_posting":2,"note":null},{"subarea_name":"足柄上郡大井町柳","total_posting":681,"recently_posting":37,"note":null},{"subarea_name":"足柄上郡大井町金子中の町","total_posting":642,"recently_posting":23,"note":null},{"subarea_name":"足柄上郡大井町金子深町","total_posting":785,"recently_posting":37,"note":null}]